pespace/__init__.py
pespace/waveform_old.py
pespace/detector/__init__.py
pespace/detector/antenna.py
pespace/detector/noise.py
pespace/detector/orbit.py
pespace/detector/tdi.py
pespace/inference/__init__.py
pespace/inference/_likelihood_old.py
pespace/inference/common.py
pespace/inference/fisher.py
pespace/inference/interface_bilby.py
pespace/inference/interface_pycbc.py
pespace/utils/__init__.py
pespace/utils/constants.py
pespace/utils/utils.py
pespace/waveform/__init__.py
pespace/waveform/interface_lalsim.py
pespace-0.0.0.dist-info/licenses/LICENSE
pespace-0.0.0.dist-info/METADATA
pespace-0.0.0.dist-info/WHEEL
pespace-0.0.0.dist-info/top_level.txt
pespace-0.0.0.dist-info/RECORD
