Metadata-Version: 2.4
Name: pespace
Version: 0.0.0
Summary: A tool for parameter estimation with space-borne gravitational-wave detectors.
Author-email: Rui Niu <nrui@mail.ustc.edu.cn>
License-Expression: GPL-3.0-or-later
Project-URL: Documentation, https://github.com/nnrui/pespace
Project-URL: Repository, https://github.com/nnrui/pespace
Keywords: gravitational-wave,taichi-lang,parameter estimation
Classifier: Development Status :: 2 - Pre-Alpha
Classifier: Intended Audience :: Science/Research
Classifier: Programming Language :: Python :: 3
Classifier: Topic :: Scientific/Engineering :: Astronomy
Requires-Python: >=3.10
License-File: LICENSE
Requires-Dist: taichi!=1.7.1
Requires-Dist: numpy
Requires-Dist: scipy
Requires-Dist: matplotlib
Requires-Dist: tiwave
Provides-Extra: dev
Requires-Dist: pytest; extra == "dev"
Requires-Dist: pytest-cov; extra == "dev"
Requires-Dist: black; extra == "dev"
Requires-Dist: mypy; extra == "dev"
Requires-Dist: sphinx; extra == "dev"
Dynamic: license-file
